README.md
setup.py
VKML/__init__.py
VKML.egg-info/PKG-INFO
VKML.egg-info/SOURCES.txt
VKML.egg-info/dependency_links.txt
VKML.egg-info/top_level.txt
VKML/gui/__init__.py
VKML/gui/tk/Gui.py
VKML/gui/tk/Menu.py
VKML/gui/tk/Parameter.py
VKML/gui/tk/VKMLgui.py
VKML/gui/tk/__init__.py
VKML/gui/tk/ttip.py