Metadata-Version: 1.0
Name: VKML
Version: 1.2
Summary: VKML: Virtual Kinetics of Materials Laboratory
Home-page: https://github.itap.purdue.edu/garciagroup/VKML
Author: Surya Mitra, Edwin Garcia, Alex Bartol, Jarrod Lund
Author-email: sayalaso@purdue.edu,redwing@purdue.edu
License: GNU GPLv3
Platform: UNKNOWN
